analise_atividade_fisica_bykelvin/__init__.py
analise_atividade_fisica_bykelvin/analysis.py
analise_atividade_fisica_bykelvin/loader.py
analise_atividade_fisica_bykelvin-0.0.1.dist-info/METADATA
analise_atividade_fisica_bykelvin-0.0.1.dist-info/WHEEL
analise_atividade_fisica_bykelvin-0.0.1.dist-info/top_level.txt
analise_atividade_fisica_bykelvin-0.0.1.dist-info/RECORD
