Metadata-Version: 2.4
Name: analise-atividade-fisica-bykelvin
Version: 0.0.1
Summary: Pacote para análise de atividades físicas com base em CSV
Author: Kelvin
Requires-Dist: pandas
Dynamic: author
Dynamic: requires-dist
Dynamic: summary
